xdiff/__init__.py
xdiff/cli.py
xdiff/core.py
xdiff/helpers.py
xdiff-0.1.0.dist-info/DESCRIPTION.rst
xdiff-0.1.0.dist-info/METADATA
xdiff-0.1.0.dist-info/RECORD
xdiff-0.1.0.dist-info/WHEEL
xdiff-0.1.0.dist-info/entry_points.txt
xdiff-0.1.0.dist-info/metadata.json
xdiff-0.1.0.dist-info/top_level.txt
