Metadata-Version: 2.0
Name: xdiff
Version: 0.1.0
Summary: A CLI tool to compare data structures, files, folders, http responses, etc.
Home-page: https://github.com/debugtalk/xdiff.git
Author: Leo Lee
Author-email: mail@debugtalk.com
License: MIT
Platform: UNKNOWN
Classifier: Programming Language :: Python :: 2.7
Classifier: Programming Language :: Python :: 3
Requires-Dist: PyYAML
Requires-Dist: future
Requires-Dist: termcolor
